{
  "difficulties": {
    "easy": {
      "name": "简单",
      "nameEn": "Easy",
      "enemyCount": {
        "min": 3,
        "max": 5
      },
      "aiLevel": 0.8,
      "unlockCondition": null
    },
    "normal": {
      "name": "普通",
      "nameEn": "Normal",
      "enemyCount": {
        "min": 5,
        "max": 8
      },
      "aiLevel": 1.0,
      "unlockCondition": {
        "type": "beatDifficulty",
        "requiredDifficulty": "easy"
      }
    },
    "hard": {
      "name": "困难",
      "nameEn": "Hard",
      "enemyCount": {
        "min": 8,
        "max": 12
      },
      "aiLevel": 1.2,
      "unlockCondition": {
        "type": "reachLevel",
        "requiredLevel": 10
      }
    }
  },
  "defaultDifficulty": "easy"
}
